MANIFEST.in
graphios.cfg
graphios.py
graphios_backends.py
setup.cfg
setup.py
graphios.egg-info/PKG-INFO
graphios.egg-info/SOURCES.txt
graphios.egg-info/dependency_links.txt
graphios.egg-info/top_level.txt
init/debian/graphios
init/debian/graphios.conf
init/rhel/graphios
init/rhel/install
init/rhel/postinstall
init/rhel/postuninstall
init/systemd/graphios.service
nagios/graphios_commands.cfg
nagios/nagios_perfdata.cfg