Metadata-Version: 1.1
Name: graphios
Version: 2.0.3
Summary: Emit Nagios metrics to Graphite, Statsd, and Librato
Home-page: https://github.com/shawn-sterling/graphios
Author: Shawn Sterling
Author-email: shawn@systemtemplar.org
License: GPL v2
Keywords: Nagios metrics graphing visualization
Platform: UNKNOWN
Classifier: Intended Audience :: System Administrators
Classifier: Programming Language :: Python :: 2.7
